catherder/__init__.py
catherder/classes.py
catherder/config.py
catherder/fix_path.py
catherder/names.py
catherder/update.py
catherder/utils.py
catherder-0.1.1.dist-info/LICENSE
catherder-0.1.1.dist-info/METADATA
catherder-0.1.1.dist-info/WHEEL
catherder-0.1.1.dist-info/entry_points.txt
catherder-0.1.1.dist-info/top_level.txt
catherder-0.1.1.dist-info/RECORD
