Metadata-Version: 2.1
Name: catherder
Version: 0.1.1
Summary: A tool for syncing different project management tools.
Home-page: https://github.com/cropsinsilico/catherder
Author: Meagan lang
Author-email: langmm.astro@gmail.com
License: MIT
Platform: UNKNOWN
Classifier: Development Status :: 2 - Pre-Alpha
Classifier: License :: OSI Approved :: MIT License
Classifier: Programming Language :: Python
Classifier: Programming Language :: Python :: 2
Classifier: Programming Language :: Python :: 2.7
Classifier: Programming Language :: Python :: 3
Classifier: Programming Language :: Python :: 3.4
Classifier: Programming Language :: Python :: 3.5
Classifier: Programming Language :: Python :: 3.6
Classifier: Programming Language :: Python :: 3.7
Requires-Dist: PyGithub
Requires-Dist: smartsheet-python-sdk
